qgis_ns_pe/__init__.py
qgis_ns_pe/cli.py
qgis_ns_pe-0.1.3.dist-info/METADATA
qgis_ns_pe-0.1.3.dist-info/WHEEL
qgis_ns_pe-0.1.3.dist-info/entry_points.txt
qgis_ns_pe-0.1.3.dist-info/top_level.txt
qgis_ns_pe-0.1.3.dist-info/RECORD
