Metadata-Version: 2.4
Name: qgis-ns-pe
Version: 0.1.3
Summary: A CLI tool for processing LiDAR data from Nova Scotia and PEI using QGIS
Author-email: Amad Gakkhar <amad.gakkhar@adept-techsolutions.com>
License-Expression: MIT
Classifier: Programming Language :: Python :: 3
Classifier: Operating System :: OS Independent
Classifier: Topic :: Scientific/Engineering :: GIS
Classifier: Topic :: Scientific/Engineering :: Information Analysis
Requires-Python: >=3.8
Requires-Dist: pyproj>=3.0.0
Requires-Dist: requests>=2.25.1
Requires-Dist: laspy>=2.0.0
Requires-Dist: numpy>=1.20.0
Requires-Dist: matplotlib>=3.3.0
Requires-Dist: lazrs>=0.1.0
